README.txt
setup.py
cmsplugin_comments/__init__.py
cmsplugin_comments/admin.py
cmsplugin_comments/cms_plugins.py
cmsplugin_comments/forms.py
cmsplugin_comments/models.py
cmsplugin_comments.egg-info/PKG-INFO
cmsplugin_comments.egg-info/SOURCES.txt
cmsplugin_comments.egg-info/dependency_links.txt
cmsplugin_comments.egg-info/not-zip-safe
cmsplugin_comments.egg-info/requires.txt
cmsplugin_comments.egg-info/top_level.txt
cmsplugin_comments/migrations/0001_init.py
cmsplugin_comments/migrations/0002_auto__add_field_discussion_enable_comments.py
cmsplugin_comments/migrations/__init__.py