Metadata-Version: 1.1
Name: cmsplugin-comments
Version: 0.1
Summary: A very simple plugin for django-cms 2 to implement comments
Home-page: http://bitbucket.org/gmh04/cmsplugin_comments
Author: gmh04
Author-email: gmh04@netscape.net
License: MIT
Platform: UNKNOWN
Classifier: Development Status :: 4 - Beta
Classifier: Environment :: Web Environment
Classifier: Intended Audience :: Developers
Classifier: License :: OSI Approved :: MIT License
Classifier: Operating System :: OS Independent
Classifier: Programming Language :: Python
Classifier: Topic :: Security
Classifier: Topic :: Internet :: WWW/HTTP
Classifier: Framework :: Django
Requires: captcha
